gcs/__init__.py
gcs/discretization.py
gcs/shape.py
gcs/triangulation.py
gcs/io/__init__.py
gcs/io/load.py
gcs/io/save.py
gcs/utils/__init__.py
gcs/utils/coordinates.py
gcs/utils/polar_curves.py
gcs/utils/summed_cosine.py
gcs/verify/__init__.py
gcs/verify/verify.py
gcs/verify/verify_base_perimeter.py
gcs/verify/verify_radius.py
gcs_shape-1.3.0.dist-info/LICENSE
gcs_shape-1.3.0.dist-info/METADATA
gcs_shape-1.3.0.dist-info/WHEEL
gcs_shape-1.3.0.dist-info/top_level.txt
gcs_shape-1.3.0.dist-info/RECORD
