Metadata-Version: 2.1
Name: gcs-shape
Version: 1.3.0
Summary: Generalized cylindrical shell library for Python.
Home-page: https://github.com/bu-shapelab/gcs
Download-URL: https://pypi.python.org/pypi/gcs-shape
Author: Kelsey L. Snapp et al.
Maintainer: Samuel Silverman
Maintainer-email: sssilver@bu.edu
License: MIT
Project-URL: Bug Tracker, https://github.com/bu-shapelab/gcs/issues
Project-URL: Documentation, https://gcs-shape.readthedocs.io/
Project-URL: Source Code, https://github.com/bu-shapelab/gcs
Classifier: Development Status :: 5 - Production/Stable
Classifier: Intended Audience :: Developers
Classifier: Intended Audience :: Science/Research
Classifier: License :: OSI Approved :: MIT License
Classifier: Natural Language :: English
Classifier: Operating System :: OS Independent
Classifier: Programming Language :: Python
Classifier: Topic :: Multimedia :: Graphics :: 3D Modeling
Classifier: Topic :: Scientific/Engineering
Classifier: Topic :: Software Development :: Libraries :: Python Modules
Classifier: Typing :: Typed
Requires-Python: >=3.8
License-File: LICENSE
Requires-Dist: bentley-ottmann==7.3.0
Requires-Dist: mapbox-earcut>=1.0.0
Requires-Dist: numpy>=1.21.5
Requires-Dist: numpy-stl>=2.17.1
Requires-Dist: pandas>=1.4.1
Requires-Dist: scipy>=1.7.3
